LICENSE
README.md
setup.cfg
setup.py
parallel_sync/__init__.py
parallel_sync/compression.py
parallel_sync/downloader.py
parallel_sync/executor.py
parallel_sync/rsync.py
parallel_sync/wget.py
parallel_sync.egg-info/PKG-INFO
parallel_sync.egg-info/SOURCES.txt
parallel_sync.egg-info/dependency_links.txt
parallel_sync.egg-info/not-zip-safe
parallel_sync.egg-info/requires.txt
parallel_sync.egg-info/top_level.txt