Metadata-Version: 2.1
Name: parallel-sync
Version: 2.0.1
Summary: A Parallelized file/url syncing package
Home-page: https://github.com/kouroshparsa/parallel_sync
Download-URL: https://github.com/kouroshparsa/parallel_sync/packages/2.0.1
Author: Kourosh Parsa
Author-email: kouroshtheking@gmail.com
License: GNU
Platform: Linux
Classifier: Operating System :: Unix
Classifier: Programming Language :: Python
Requires-Python: >=3
License-File: LICENSE
